phalski_ledshim/__init__.py
phalski_ledshim/animation.py
phalski_ledshim/app.py
phalski_ledshim/chart.py
phalski_ledshim/client.py
phalski_ledshim/color.py
phalski_ledshim-0.2.2.dist-info/LICENSE
phalski_ledshim-0.2.2.dist-info/METADATA
phalski_ledshim-0.2.2.dist-info/WHEEL
phalski_ledshim-0.2.2.dist-info/top_level.txt
phalski_ledshim-0.2.2.dist-info/RECORD
