Metadata-Version: 2.1
Name: phalski-ledshim
Version: 0.2.2
Summary: A basic application framework for the Pimoroni LED SHIM
Home-page: https://github.com/phalski/phalski-ledshim
Author: phalski
Author-email: mail@phalski.com
License: UNKNOWN
Platform: UNKNOWN
Classifier: Programming Language :: Python :: 3
Classifier: License :: OSI Approved :: MIT License
Classifier: Operating System :: OS Independent
Requires-Dist: ledshim (>=0.0.1)
